toontown/__init__.py
toontown/__main__.py
toontown/exceptions.py
toontown/client/__init__.py
toontown/client/base.py
toontown/client/clash.py
toontown/client/rewritten.py
toontown/http/__init__.py
toontown/http/base.py
toontown/http/clash.py
toontown/http/rewritten.py
toontown/models/__init__.py
toontown/models/base.py
toontown/models/clash/__init__.py
toontown/models/clash/districts.py
toontown/models/clash/login.py
toontown/models/clash/news.py
toontown/models/rewritten/__init__.py
toontown/models/rewritten/doodles.py
toontown/models/rewritten/fieldoffices.py
toontown/models/rewritten/invasions.py
toontown/models/rewritten/login.py
toontown/models/rewritten/news.py
toontown/models/rewritten/population.py
toontown/models/rewritten/releasenotes.py
toontown/models/rewritten/sillymeter.py
toontown/models/rewritten/status.py
toontown.py-2.0.1.dist-info/LICENSE
toontown.py-2.0.1.dist-info/METADATA
toontown.py-2.0.1.dist-info/WHEEL
toontown.py-2.0.1.dist-info/top_level.txt
toontown.py-2.0.1.dist-info/RECORD
