Metadata-Version: 2.1
Name: toontown.py
Version: 2.0.1
Summary: A simple Python wrapper for the Toontown Rewritten API
Home-page: https://github.com/jaczerob/toontown.py
Author: jaczerob
License: MIT
Platform: UNKNOWN
Classifier: License :: OSI Approved :: MIT License
Classifier: Intended Audience :: Developers
Classifier: Natural Language :: English
Classifier: Operating System :: OS Independent
Classifier: Programming Language :: Python :: 3.8
Classifier: Programming Language :: Python :: 3.9
Classifier: Programming Language :: Python :: 3.10
Classifier: Topic :: Internet
Classifier: Topic :: Software Development :: Libraries
Classifier: Topic :: Software Development :: Libraries :: Python Modules
Classifier: Topic :: Utilities
Classifier: Topic :: Games/Entertainment
Requires-Python: >=3.8.0
License-File: LICENSE
Requires-Dist: aiohttp (==3.8.1)
Requires-Dist: requests (==2.27.1)
